joey_click_test/__init__.py
joey_click_test/main.py
joey_click_test-0.1.0.dist-info/METADATA
joey_click_test-0.1.0.dist-info/WHEEL
joey_click_test-0.1.0.dist-info/entry_points.txt
joey_click_test-0.1.0.dist-info/top_level.txt
joey_click_test-0.1.0.dist-info/RECORD
