Metadata-Version: 2.1
Name: joey-click-test
Version: 0.1.0
Requires-Dist: click
